{"lastUsed":1678280828368,"path":"C:\/Users\/unriv\/OneDrive\/Documentos\/sobrecarga_encapsulamento","projectCount":1,"recentFiles":[{"path":"\/sobrecarga_encapsulamento\/src\/entities","parentWorkspace":"C:\/Users\/unriv\/OneDrive\/Documentos\/sobrecarga_encapsulamento","name":"Account.java","lastModified":1678034605110,"locationURI":"file:\/C:\/Users\/unriv\/OneDrive\/Documentos\/sobrecarga_encapsulamento\/sobrecarga_encapsulamento\/src\/entities\/Account.java"},{"path":"\/sobrecarga_encapsulamento\/src\/application","parentWorkspace":"C:\/Users\/unriv\/OneDrive\/Documentos\/sobrecarga_encapsulamento","name":"Program.java","lastModified":1678072997606,"locationURI":"file:\/C:\/Users\/unriv\/OneDrive\/Documentos\/sobrecarga_encapsulamento\/sobrecarga_encapsulamento\/src\/application\/Program.java"}]}